memgraph/__init__.py
memgraph/__main__.py
memgraph/__version__.py
memgraph/backup.py
memgraph/config.py
memgraph/context_search.py
memgraph/embeddings.py
memgraph/launcher.py
memgraph/mcp_service.py
memgraph/service.py
memgraph/service_logging.py
memgraph/sqlite_backend.py
memgraph/stdio_service.py
memgraph/vector_sqlite.py
memgraph/vector_store.py
memgraph/web_service.py
memgraph/web/favicon.png
memgraph/web/graph.bundle.js
memgraph/web/graph.bundle.js.map
memgraph/web/index.html
memgraph/web/style.css
memgraph/web/zabob-faviicon.png
zabob_memgraph-0.1.28.dist-info/licenses/LICENSE
zabob_memgraph-0.1.28.dist-info/licenses/LICENSE.md
zabob_memgraph-0.1.28.dist-info/METADATA
zabob_memgraph-0.1.28.dist-info/WHEEL
zabob_memgraph-0.1.28.dist-info/entry_points.txt
zabob_memgraph-0.1.28.dist-info/top_level.txt
zabob_memgraph-0.1.28.dist-info/RECORD
