Metadata-Version: 2.4
Name: zabob-memgraph
Version: 0.1.28
Summary: Zabob Memgraph - Knowledge graph visualization and MCP server
Requires-Python: >=3.13
License-File: LICENSE
License-File: LICENSE.md
Requires-Dist: fastapi
Requires-Dist: uvicorn>=0.40.0
Requires-Dist: mcp>=1.26.0
Requires-Dist: fastmcp>=3.0.0b1
Requires-Dist: pydantic>=2.12.5
Requires-Dist: jinja2>=3.1.6
Requires-Dist: psutil>=7.2.2
Requires-Dist: aiofiles>=25.1.0
Requires-Dist: rich>=14.3.1
Requires-Dist: requests>=2.32.5
Requires-Dist: toml>=0.10.2
Requires-Dist: httpx>=0.28.1
Requires-Dist: sentence-transformers>=5.2.2
Requires-Dist: numpy>=2.4.1
Provides-Extra: ci
Requires-Dist: pytest>=9.0.2; extra == "ci"
Requires-Dist: pytest-xdist>=3.8.0; extra == "ci"
Requires-Dist: pytest-asyncio>=1.3.0; extra == "ci"
Requires-Dist: anyio>=4.12.1; extra == "ci"
Requires-Dist: playwright>=1.57.0; extra == "ci"
Requires-Dist: pytest-playwright>=0.7.2; extra == "ci"
Requires-Dist: ruff>=0.14.14; extra == "ci"
Requires-Dist: mypy>=1.19.1; extra == "ci"
Requires-Dist: types-psutil>=7.2.1.20260116; extra == "ci"
Requires-Dist: types-requests>=2.32.4.20260107; extra == "ci"
Provides-Extra: dev
Requires-Dist: pytest>=9.0.2; extra == "dev"
Requires-Dist: pytest-xdist>=3.8.0; extra == "dev"
Requires-Dist: pytest-asyncio>=1.3.0; extra == "dev"
Requires-Dist: anyio>=4.12.1; extra == "dev"
Requires-Dist: playwright>=1.57.0; extra == "dev"
Requires-Dist: pytest-playwright>=0.7.2; extra == "dev"
Requires-Dist: ruff>=0.14.14; extra == "dev"
Requires-Dist: mypy>=1.19.1; extra == "dev"
Requires-Dist: watchfiles>=1.1.1; extra == "dev"
Requires-Dist: black>=26.1.0; extra == "dev"
Requires-Dist: isort>=7.0.0; extra == "dev"
Requires-Dist: types-psutil>=7.2.1.20260116; extra == "dev"
Requires-Dist: types-requests>=2.32.4.20260107; extra == "dev"
Dynamic: license-file
